AUTHORS.rst
CONTRIBUTING.rst
HISTORY.rst
LICENSE
README.rst
autosequence/__init__.py
autosequence/fields.py
autosequence/helpers.py
django_autosequence-0.8.0.dist-info/LICENSE
django_autosequence-0.8.0.dist-info/WHEEL
django_autosequence-0.8.0.dist-info/METADATA
django_autosequence-0.8.0.dist-info/RECORD
