Metadata-Version: 2.1
Name: django-autosequence
Version: 0.8.0
Summary: A Django model field providing a configurable automatic sequence of values.
Home-page: https://github.com/cordery/django-autosequence
License: MIT
Keywords: Django
Author: Andrew Cordery
Author-email: cordery@gmail.com
Requires-Python: >=3.7,<4
Classifier: Development Status :: 5 - Production/Stable
Classifier: Framework :: Django
Classifier: Framework :: Django :: 2.2
Classifier: Framework :: Django :: 3.0
Classifier: Framework :: Django :: 4.0
Classifier: Intended Audience :: Developers
Classifier: License :: OSI Approved :: MIT License
Classifier: Natural Language :: English
Classifier: Programming Language :: Python :: 3
Classifier: Programming Language :: Python :: 3.10
Classifier: Programming Language :: Python :: 3.7
Classifier: Programming Language :: Python :: 3.8
Classifier: Programming Language :: Python :: 3.9
Requires-Dist: django (>=2.2)
Project-URL: Repository, https://github.com/cordery/django-autosequence
